{
    "title": {
        "evaluators": {
            "levenshtein": 1.0
        }
    },
    "author": {
        "evaluators": {
            "boolean": 1.0
        }
    },
    "doi": {
        "evaluators": {
            "boolean": 1.0
        }
    },
    "date": {
        "evaluators": {
            "levenshtein": 1.0
        }
    },
    "volume": {
        "evaluators": {
            "levenshtein": 1.0
        }
    },
    "pages": {
        "evaluators": {
            "boolean": 1.0
        }
    }
}